kserve/__init__.py
kserve/api/__init__.py
kserve/api/creds_utils.py
kserve/api/kserve_client.py
kserve/api/watch.py
kserve/api_client.py
kserve/configuration.py
kserve/constants/__init__.py
kserve/constants/constants.py
kserve/errors.py
kserve/exceptions.py
kserve/inference_client.py
kserve/logging.py
kserve/metrics.py
kserve/model.py
kserve/model_repository.py
kserve/model_server.py
kserve/models/__init__.py
kserve/models/knative_addressable.py
kserve/models/knative_condition.py
kserve/models/knative_status.py
kserve/models/knative_url.py
kserve/models/knative_volatile_time.py
kserve/models/net_url_userinfo.py
kserve/models/v1_time.py
kserve/models/v1alpha1_built_in_adapter.py
kserve/models/v1alpha1_cluster_serving_runtime.py
kserve/models/v1alpha1_cluster_serving_runtime_list.py
kserve/models/v1alpha1_cluster_storage_container.py
kserve/models/v1alpha1_cluster_storage_container_list.py
kserve/models/v1alpha1_container.py
kserve/models/v1alpha1_inference_graph.py
kserve/models/v1alpha1_inference_graph_list.py
kserve/models/v1alpha1_inference_graph_spec.py
kserve/models/v1alpha1_inference_graph_status.py
kserve/models/v1alpha1_inference_router.py
kserve/models/v1alpha1_inference_step.py
kserve/models/v1alpha1_inference_target.py
kserve/models/v1alpha1_local_model_cache.py
kserve/models/v1alpha1_local_model_cache_list.py
kserve/models/v1alpha1_local_model_cache_spec.py
kserve/models/v1alpha1_local_model_node.py
kserve/models/v1alpha1_local_model_node_group.py
kserve/models/v1alpha1_local_model_node_group_list.py
kserve/models/v1alpha1_local_model_node_group_spec.py
kserve/models/v1alpha1_local_model_node_list.py
kserve/models/v1alpha1_local_model_node_spec.py
kserve/models/v1alpha1_model_spec.py
kserve/models/v1alpha1_serving_runtime.py
kserve/models/v1alpha1_serving_runtime_list.py
kserve/models/v1alpha1_serving_runtime_pod_spec.py
kserve/models/v1alpha1_serving_runtime_spec.py
kserve/models/v1alpha1_storage_container_spec.py
kserve-0.15.1.dist-info/METADATA
kserve-0.15.1.dist-info/WHEEL
kserve-0.15.1.dist-info/RECORD
