Metadata-Version: 2.1
Name: kserve
Version: 0.15.1
Summary: KServe Python SDK
Home-page: https://github.com/kserve/kserve/tree/master/python/kserve
License: Apache-2.0
Author: The KServe Authors
Author-email: dsun20@bloomberg.net
Requires-Python: >=3.9,<3.13
Classifier: Intended Audience :: Developers
Classifier: Intended Audience :: Education
Classifier: Intended Audience :: Science/Research
Classifier: License :: OSI Approved :: Apache Software License
Classifier: Operating System :: OS Independent
Classifier: Programming Language :: Python :: 3
Classifier: Programming Language :: Python :: 3.9
Classifier: Programming Language :: Python :: 3.10
Classifier: Programming Language :: Python :: 3.11
Classifier: Programming Language :: Python :: 3.12
Classifier: Topic :: Scientific/Engineering
Classifier: Topic :: Scientific/Engineering :: Artificial Intelligence
Classifier: Topic :: Software Development
Classifier: Topic :: Software Development :: Libraries
Classifier: Topic :: Software Development :: Libraries :: Python Modules
Provides-Extra: llm
Provides-Extra: logging
Provides-Extra: ray
Provides-Extra: storage
Requires-Dist: asgi-logger (>=0.1.0,<0.2.0) ; extra == "logging"
Requires-Dist: azure-identity (>=1.15.0,<2.0.0) ; extra == "storage"
Requires-Dist: azure-storage-blob (>=12.20.0,<13.0.0) ; extra == "storage"
Requires-Dist: azure-storage-file-share (>=12.16.0,<13.0.0) ; extra == "storage"
Requires-Dist: boto3 (>=1.29.0,<2.0.0) ; extra == "storage"
Requires-Dist: cloudevents (>=1.6.2,<2.0.0)
Requires-Dist: fastapi (>=0.115.3)
Requires-Dist: google-cloud-storage (>=2.14.0,<3.0.0) ; extra == "storage"
Requires-Dist: grpc-interceptor (>=0.15.4,<1.0.0)
Requires-Dist: grpcio (>=1.60.0,<2.0.0)
Requires-Dist: httpx (>=0.27.2,<0.28.0)
Requires-Dist: huggingface-hub[hf-transfer] (>=0.30.0,<0.31.0) ; extra == "storage"
Requires-Dist: kubernetes (>=23.3.0)
Requires-Dist: numpy (>=1.26.0,<3.0.0)
Requires-Dist: orjson (>=3.9.15,<4.0.0)
Requires-Dist: pandas (>=2.2.0,<3.0.0)
Requires-Dist: prometheus-client (>=0.20.0,<0.21.0)
Requires-Dist: protobuf (>=4.25.4,<5.0.0)
Requires-Dist: psutil (>=5.9.6,<6.0.0)
Requires-Dist: pydantic (>1.0,<3) ; python_version >= "3.9" and python_version < "3.12"
Requires-Dist: pydantic (>=2.5.0,<3.0.0) ; python_version == "3.12"
Requires-Dist: python-dateutil (>=2.8.0,<3.0.0)
Requires-Dist: pyyaml (>=6.0.0,<7.0.0)
Requires-Dist: ray[serve] (>=2.43.0) ; extra == "ray"
Requires-Dist: requests (>=2.32.2,<3.0.0) ; extra == "storage"
Requires-Dist: six (>=1.16.0,<2.0.0)
Requires-Dist: tabulate (>=0.9.0,<0.10.0)
Requires-Dist: timing-asgi (>=0.3.0,<0.4.0)
Requires-Dist: uvicorn[standard] (>=0.30.6,<0.31.0)
Requires-Dist: vllm (==0.8.5) ; extra == "llm"
Project-URL: Repository, https://github.com/kserve/kserve/tree/master/python/kserve
